mowitnow/__init__.py
mowitnow-0.3.dist-info/METADATA
mowitnow-0.3.dist-info/WHEEL
mowitnow-0.3.dist-info/top_level.txt
mowitnow-0.3.dist-info/RECORD
