Metadata-Version: 2.1
Name: mowitnow
Version: 0.3
Summary: MowItNow controller
Home-page: https://github.com/xavbyme/mowitnow.git
Author: XRU
Author-email: ruiz.xvr@gmail.com
License: MIT
Platform: UNKNOWN
